{
  "project_info": {
    "project_number": "1041712138611",
    "project_id": "money-minder-2023",
    "storage_bucket": "money-minder-2023.appspot.com"
  },
  "client": [
    {
      "client_info": {
        "mobilesdk_app_id": "1:1041712138611:android:506ee9418313557fb19d06",
        "android_client_info": {
          "package_name": "com.example.money_minder"
        }
      },
      "oauth_client": [],
      "api_key": [
        {
          "current_key": "AIzaSyAsID39NBXtHwGfRioFdkUT0yWc3KWkhc8"
        }
      ],
      "services": {
        "appinvite_service": {
          "other_platform_oauth_client": []
        }
      }
    }
  ],
  "configuration_version": "1"
}